lesting.api-0.0.1-py3.9-nspkg.pth
build/lib/build/lib/lesting/api/__init__.py
build/lib/build/lib/lesting/api/fields.py
build/lib/build/lib/lesting/api/resources.py
build/lib/build/lib/lesting/api/schemas.py
build/lib/build/lib/lesting/api/client/__init__.py
build/lib/build/lib/lesting/api/client/discovery.py
build/lib/build/lib/lesting/api/client/resources.py
build/lib/build/lib/lesting/api/server/base.py
build/lib/build/lib/lesting/api/server/framework/flask.py
build/lib/lesting/api/__init__.py
build/lib/lesting/api/fields.py
build/lib/lesting/api/resources.py
build/lib/lesting/api/schemas.py
build/lib/lesting/api/client/__init__.py
build/lib/lesting/api/client/discovery.py
build/lib/lesting/api/client/resources.py
build/lib/lesting/api/server/base.py
build/lib/lesting/api/server/framework/flask.py
lesting/api/__init__.py
lesting/api/fields.py
lesting/api/resources.py
lesting/api/schemas.py
lesting/api/client/__init__.py
lesting/api/client/discovery.py
lesting/api/client/resources.py
lesting/api/server/base.py
lesting/api/server/framework/flask.py
lesting.api-0.0.1.dist-info/LICENSE
lesting.api-0.0.1.dist-info/METADATA
lesting.api-0.0.1.dist-info/WHEEL
lesting.api-0.0.1.dist-info/namespace_packages.txt
lesting.api-0.0.1.dist-info/top_level.txt
lesting.api-0.0.1.dist-info/RECORD
